{
  "uid": "perfmon-instance",
  "title": "PerfMon · Overview",
  "tags": [
    "perfmon"
  ],
  "timezone": "",
  "schemaVersion": 39,
  "editable": true,
  "graphTooltip": 1,
  "fiscalYearStartMonth": 0,
  "time": {
    "from": "now-3h",
    "to": "now"
  },
  "refresh": "1m",
  "weekStart": "",
  "annotations": {
    "list": []
  },
  "links": [
    {
      "title": "Fleet Overview",
      "icon": "dashboard",
      "type": "link",
      "url": "/d/perfmon-fleet?${__url_time_range}",
      "keepTime": true,
      "includeVars": false,
      "targetBlank": false
    },
    {
      "asDropdown": true,
      "icon": "external link",
      "includeVars": true,
      "keepTime": true,
      "tags": [
        "perfmon"
      ],
      "targetBlank": false,
      "title": "All PerfMon Dashboards",
      "type": "dashboards",
      "url": ""
    },
    {
      "asDropdown": true,
      "icon": "external link",
      "includeVars": true,
      "keepTime": true,
      "tags": [
        "finops"
      ],
      "targetBlank": false,
      "title": "All FinOps Dashboards",
      "type": "dashboards",
      "url": ""
    }
  ],
  "templating": {
    "list": [
      {
        "name": "instance",
        "label": "Instance",
        "type": "datasource",
        "query": "mssql",
        "regex": "/^PerfMon-/",
        "current": {},
        "options": [],
        "refresh": 1,
        "hide": 0,
        "multi": false,
        "includeAll": false,
        "sort": 1,
        "description": "Monitored SQL Server instance - one MSSQL datasource per instance. Type to search."
      }
    ]
  },
  "panels": [
    {
      "id": 1,
      "type": "row",
      "title": "Resource Overview",
      "collapsed": false,
      "gridPos": {
        "h": 1,
        "w": 24,
        "x": 0,
        "y": 0
      },
      "panels": []
    },
    {
      "id": 2,
      "type": "stat",
      "title": "CPU (now)",
      "datasource": {
        "type": "mssql",
        "uid": "${instance}"
      },
      "gridPos": {
        "h": 4,
        "w": 4,
        "x": 0,
        "y": 1
      },
      "fieldConfig": {
        "defaults": {
          "color": {
            "mode": "thresholds"
          },
          "decimals": 0,
          "thresholds": {
            "mode": "absolute",
            "steps": [
              {
                "color": "green",
                "value": null
              },
              {
                "color": "yellow",
                "value": 70
              },
              {
                "color": "red",
                "value": 90
              }
            ]
          },
          "unit": "percent"
        },
        "overrides": []
      },
      "options": {
        "reduceOptions": {
          "calcs": [
            "lastNotNull"
          ],
          "fields": "",
          "values": false
        },
        "colorMode": "background",
        "graphMode": "none",
        "justifyMode": "auto",
        "orientation": "auto",
        "textMode": "auto"
      },
      "targets": [
        {
          "refId": "A",
          "datasource": {
            "type": "mssql",
            "uid": "${instance}"
          },
          "format": "table",
          "rawQuery": true,
          "rawSql": "SELECT TOP (1) cpu = ISNULL(total_cpu_utilization, sqlserver_cpu_utilization) FROM collect.cpu_utilization_stats ORDER BY collection_time DESC;"
        }
      ]
    },
    {
      "id": 3,
      "type": "stat",
      "title": "Buffer pool % of target (now)",
      "datasource": {
        "type": "mssql",
        "uid": "${instance}"
      },
      "gridPos": {
        "h": 4,
        "w": 4,
        "x": 4,
        "y": 1
      },
      "fieldConfig": {
        "defaults": {
          "color": {
            "mode": "thresholds"
          },
          "decimals": 0,
          "thresholds": {
            "mode": "absolute",
            "steps": [
              {
                "color": "blue",
                "value": null
              }
            ]
          },
          "unit": "percent"
        },
        "overrides": []
      },
      "options": {
        "reduceOptions": {
          "calcs": [
            "lastNotNull"
          ],
          "fields": "",
          "values": false
        },
        "colorMode": "background",
        "graphMode": "none",
        "justifyMode": "auto",
        "orientation": "auto",
        "textMode": "auto"
      },
      "targets": [
        {
          "refId": "A",
          "datasource": {
            "type": "mssql",
            "uid": "${instance}"
          },
          "format": "table",
          "rawQuery": true,
          "rawSql": "SELECT TOP (1) mem = buffer_pool_mb * 100.0 / NULLIF(committed_target_memory_mb, 0) FROM collect.memory_stats ORDER BY collection_time DESC;"
        }
      ]
    },
    {
      "id": 4,
      "type": "stat",
      "title": "Sessions (running)",
      "datasource": {
        "type": "mssql",
        "uid": "${instance}"
      },
      "gridPos": {
        "h": 4,
        "w": 4,
        "x": 8,
        "y": 1
      },
      "fieldConfig": {
        "defaults": {
          "color": {
            "mode": "thresholds"
          },
          "decimals": 0,
          "thresholds": {
            "mode": "absolute",
            "steps": [
              {
                "color": "blue",
                "value": null
              }
            ]
          },
          "unit": "short"
        },
        "overrides": []
      },
      "options": {
        "reduceOptions": {
          "calcs": [
            "lastNotNull"
          ],
          "fields": "",
          "values": false
        },
        "colorMode": "background",
        "graphMode": "none",
        "justifyMode": "auto",
        "orientation": "auto",
        "textMode": "auto"
      },
      "targets": [
        {
          "refId": "A",
          "datasource": {
            "type": "mssql",
            "uid": "${instance}"
          },
          "format": "table",
          "rawQuery": true,
          "rawSql": "SELECT TOP (1) running = running_sessions FROM collect.session_stats ORDER BY collection_time DESC;"
        }
      ]
    },
    {
      "id": 5,
      "type": "stat",
      "title": "Blocked tasks (now)",
      "datasource": {
        "type": "mssql",
        "uid": "${instance}"
      },
      "gridPos": {
        "h": 4,
        "w": 4,
        "x": 12,
        "y": 1
      },
      "fieldConfig": {
        "defaults": {
          "color": {
            "mode": "thresholds"
          },
          "decimals": 0,
          "thresholds": {
            "mode": "absolute",
            "steps": [
              {
                "color": "green",
                "value": null
              },
              {
                "color": "yellow",
                "value": 1
              },
              {
                "color": "red",
                "value": 10
              }
            ]
          },
          "unit": "short"
        },
        "overrides": []
      },
      "options": {
        "reduceOptions": {
          "calcs": [
            "lastNotNull"
          ],
          "fields": "",
          "values": false
        },
        "colorMode": "background",
        "graphMode": "none",
        "justifyMode": "auto",
        "orientation": "auto",
        "textMode": "auto"
      },
      "targets": [
        {
          "refId": "A",
          "datasource": {
            "type": "mssql",
            "uid": "${instance}"
          },
          "format": "table",
          "rawQuery": true,
          "rawSql": "SELECT TOP (1) blocked = total_blocked_task_count FROM collect.cpu_scheduler_stats ORDER BY collection_time DESC;"
        }
      ]
    },
    {
      "id": 6,
      "type": "stat",
      "title": "Deadlocks (range)",
      "datasource": {
        "type": "mssql",
        "uid": "${instance}"
      },
      "gridPos": {
        "h": 4,
        "w": 4,
        "x": 16,
        "y": 1
      },
      "fieldConfig": {
        "defaults": {
          "color": {
            "mode": "thresholds"
          },
          "decimals": 0,
          "thresholds": {
            "mode": "absolute",
            "steps": [
              {
                "color": "green",
                "value": null
              },
              {
                "color": "yellow",
                "value": 1
              },
              {
                "color": "red",
                "value": 5
              }
            ]
          },
          "unit": "short"
        },
        "overrides": []
      },
      "options": {
        "reduceOptions": {
          "calcs": [
            "lastNotNull"
          ],
          "fields": "",
          "values": false
        },
        "colorMode": "background",
        "graphMode": "none",
        "justifyMode": "auto",
        "orientation": "auto",
        "textMode": "auto"
      },
      "targets": [
        {
          "refId": "A",
          "datasource": {
            "type": "mssql",
            "uid": "${instance}"
          },
          "format": "table",
          "rawQuery": true,
          "rawSql": "SELECT deadlocks = ISNULL(SUM(bds.deadlock_count_delta), 0) FROM collect.blocking_deadlock_stats AS bds WHERE bds.collection_time >= DATEADD(MINUTE, DATEDIFF(MINUTE, GETUTCDATE(), GETDATE()), CONVERT(datetime2, $__timeFrom())) AND bds.collection_time < DATEADD(MINUTE, DATEDIFF(MINUTE, GETUTCDATE(), GETDATE()), CONVERT(datetime2, $__timeTo()));"
        }
      ]
    },
    {
      "id": 7,
      "type": "stat",
      "title": "Collectors unhealthy",
      "datasource": {
        "type": "mssql",
        "uid": "${instance}"
      },
      "gridPos": {
        "h": 4,
        "w": 4,
        "x": 20,
        "y": 1
      },
      "fieldConfig": {
        "defaults": {
          "color": {
            "mode": "thresholds"
          },
          "decimals": 0,
          "thresholds": {
            "mode": "absolute",
            "steps": [
              {
                "color": "green",
                "value": null
              },
              {
                "color": "yellow",
                "value": 1
              },
              {
                "color": "red",
                "value": 3
              }
            ]
          },
          "unit": "short"
        },
        "overrides": []
      },
      "options": {
        "reduceOptions": {
          "calcs": [
            "lastNotNull"
          ],
          "fields": "",
          "values": false
        },
        "colorMode": "background",
        "graphMode": "none",
        "justifyMode": "auto",
        "orientation": "auto",
        "textMode": "auto"
      },
      "targets": [
        {
          "refId": "A",
          "datasource": {
            "type": "mssql",
            "uid": "${instance}"
          },
          "format": "table",
          "rawQuery": true,
          "rawSql": "SELECT unhealthy = COUNT_BIG(DISTINCT cl.collector_name) FROM config.collection_log AS cl WHERE cl.collection_time >= DATEADD(MINUTE, -5, SYSDATETIME()) AND cl.collection_status = N'ERROR';"
        }
      ]
    },
    {
      "id": 8,
      "type": "table",
      "title": "Server info",
      "datasource": {
        "type": "mssql",
        "uid": "${instance}"
      },
      "gridPos": {
        "h": 4,
        "w": 24,
        "x": 0,
        "y": 5
      },
      "fieldConfig": {
        "defaults": {
          "custom": {
            "align": "auto",
            "cellOptions": {
              "type": "auto"
            },
            "filterable": true
          },
          "thresholds": {
            "mode": "absolute",
            "steps": [
              {
                "color": "green",
                "value": null
              }
            ]
          }
        },
        "overrides": []
      },
      "options": {
        "showHeader": true,
        "cellHeight": "sm",
        "footer": {
          "show": false,
          "reducer": [
            "sum"
          ],
          "fields": ""
        },
        "sortBy": []
      },
      "targets": [
        {
          "refId": "A",
          "datasource": {
            "type": "mssql",
            "uid": "${instance}"
          },
          "format": "table",
          "rawQuery": true,
          "rawSql": "SELECT si.server_name, si.sql_version, si.edition, si.cpu_count, si.physical_memory_mb, si.environment_type, si.uptime_days, si.sqlserver_start_time FROM config.server_info AS si;"
        }
      ]
    },
    {
      "id": 9,
      "type": "timeseries",
      "title": "CPU utilization",
      "datasource": {
        "type": "mssql",
        "uid": "${instance}"
      },
      "gridPos": {
        "h": 9,
        "w": 12,
        "x": 0,
        "y": 9
      },
      "fieldConfig": {
        "defaults": {
          "color": {
            "mode": "palette-classic"
          },
          "custom": {
            "drawStyle": "line",
            "lineInterpolation": "smooth",
            "lineWidth": 1,
            "fillOpacity": 12,
            "showPoints": "never",
            "spanNulls": true,
            "stacking": {
              "mode": "normal",
              "group": "A"
            }
          },
          "unit": "percent",
          "max": 100,
          "min": 0
        },
        "overrides": []
      },
      "options": {
        "legend": {
          "displayMode": "list",
          "placement": "bottom",
          "showLegend": true,
          "calcs": []
        },
        "tooltip": {
          "mode": "multi",
          "sort": "desc"
        }
      },
      "targets": [
        {
          "refId": "A",
          "datasource": {
            "type": "mssql",
            "uid": "${instance}"
          },
          "format": "time_series",
          "rawQuery": true,
          "rawSql": "SELECT time = DATEADD(MINUTE, DATEDIFF(MINUTE, GETDATE(), GETUTCDATE()), cus.sample_time), sql_server = cus.sqlserver_cpu_utilization, other_processes = cus.other_process_cpu_utilization, total_cpu = ISNULL(cus.total_cpu_utilization, cus.sqlserver_cpu_utilization) FROM collect.cpu_utilization_stats AS cus WHERE cus.sample_time >= DATEADD(MINUTE, DATEDIFF(MINUTE, GETUTCDATE(), GETDATE()), CONVERT(datetime2, $__timeFrom())) AND cus.sample_time < DATEADD(MINUTE, DATEDIFF(MINUTE, GETUTCDATE(), GETDATE()), CONVERT(datetime2, $__timeTo())) ORDER BY cus.sample_time;"
        }
      ]
    },
    {
      "id": 10,
      "type": "timeseries",
      "title": "Memory utilization",
      "datasource": {
        "type": "mssql",
        "uid": "${instance}"
      },
      "gridPos": {
        "h": 9,
        "w": 12,
        "x": 12,
        "y": 9
      },
      "fieldConfig": {
        "defaults": {
          "color": {
            "mode": "palette-classic"
          },
          "custom": {
            "drawStyle": "line",
            "lineInterpolation": "smooth",
            "lineWidth": 1,
            "fillOpacity": 12,
            "showPoints": "never",
            "spanNulls": true,
            "stacking": {
              "mode": "none",
              "group": "A"
            }
          },
          "unit": "decmbytes"
        },
        "overrides": []
      },
      "options": {
        "legend": {
          "displayMode": "list",
          "placement": "bottom",
          "showLegend": true,
          "calcs": []
        },
        "tooltip": {
          "mode": "multi",
          "sort": "desc"
        }
      },
      "targets": [
        {
          "refId": "A",
          "datasource": {
            "type": "mssql",
            "uid": "${instance}"
          },
          "format": "time_series",
          "rawQuery": true,
          "rawSql": "\nSELECT\n    time = DATEADD(MINUTE, DATEDIFF(MINUTE, GETDATE(), GETUTCDATE()), ms.collection_time),\n    buffer_pool = ms.buffer_pool_mb,\n    plan_cache = ms.plan_cache_mb,\n    other = ms.other_memory_mb,\n    available_os_memory = ms.available_physical_memory_mb,\n    granted_memory_mb = ISNULL((\n        SELECT TOP (1)\n            SUM(mgs.granted_memory_mb)\n        FROM collect.memory_grant_stats AS mgs\n        WHERE mgs.collection_time >= DATEADD(MINUTE, -5, ms.collection_time)\n            AND mgs.collection_time <= DATEADD(MINUTE, 5, ms.collection_time)\n        GROUP BY mgs.collection_time\n        ORDER BY ABS(DATEDIFF(SECOND, mgs.collection_time, ms.collection_time)) ASC\n    ), 0)\nFROM collect.memory_stats AS ms\nWHERE ms.collection_time >= DATEADD(MINUTE, DATEDIFF(MINUTE, GETUTCDATE(), GETDATE()), CONVERT(datetime2, $__timeFrom())) AND ms.collection_time < DATEADD(MINUTE, DATEDIFF(MINUTE, GETUTCDATE(), GETDATE()), CONVERT(datetime2, $__timeTo()))\nORDER BY ms.collection_time;\n"
        }
      ]
    },
    {
      "id": 11,
      "type": "timeseries",
      "title": "Scheduler pressure",
      "datasource": {
        "type": "mssql",
        "uid": "${instance}"
      },
      "gridPos": {
        "h": 8,
        "w": 12,
        "x": 0,
        "y": 18
      },
      "fieldConfig": {
        "defaults": {
          "color": {
            "mode": "palette-classic"
          },
          "custom": {
            "drawStyle": "line",
            "lineInterpolation": "smooth",
            "lineWidth": 1,
            "fillOpacity": 12,
            "showPoints": "never",
            "spanNulls": true,
            "stacking": {
              "mode": "none",
              "group": "A"
            }
          },
          "unit": "short"
        },
        "overrides": []
      },
      "options": {
        "legend": {
          "displayMode": "list",
          "placement": "bottom",
          "showLegend": true,
          "calcs": []
        },
        "tooltip": {
          "mode": "multi",
          "sort": "desc"
        }
      },
      "targets": [
        {
          "refId": "A",
          "datasource": {
            "type": "mssql",
            "uid": "${instance}"
          },
          "format": "time_series",
          "rawQuery": true,
          "rawSql": "SELECT time = DATEADD(MINUTE, DATEDIFF(MINUTE, GETDATE(), GETUTCDATE()), css.collection_time), avg_runnable_tasks = css.avg_runnable_tasks_count, blocked_tasks = css.total_blocked_task_count, queued_requests = css.total_queued_request_count FROM collect.cpu_scheduler_stats AS css WHERE css.collection_time >= DATEADD(MINUTE, DATEDIFF(MINUTE, GETUTCDATE(), GETDATE()), CONVERT(datetime2, $__timeFrom())) AND css.collection_time < DATEADD(MINUTE, DATEDIFF(MINUTE, GETUTCDATE(), GETDATE()), CONVERT(datetime2, $__timeTo())) ORDER BY css.collection_time;"
        }
      ]
    },
    {
      "id": 12,
      "type": "timeseries",
      "title": "Sessions",
      "datasource": {
        "type": "mssql",
        "uid": "${instance}"
      },
      "gridPos": {
        "h": 8,
        "w": 12,
        "x": 12,
        "y": 18
      },
      "fieldConfig": {
        "defaults": {
          "color": {
            "mode": "palette-classic"
          },
          "custom": {
            "drawStyle": "line",
            "lineInterpolation": "smooth",
            "lineWidth": 1,
            "fillOpacity": 12,
            "showPoints": "never",
            "spanNulls": true,
            "stacking": {
              "mode": "none",
              "group": "A"
            }
          },
          "unit": "short"
        },
        "overrides": []
      },
      "options": {
        "legend": {
          "displayMode": "list",
          "placement": "bottom",
          "showLegend": true,
          "calcs": []
        },
        "tooltip": {
          "mode": "multi",
          "sort": "desc"
        }
      },
      "targets": [
        {
          "refId": "A",
          "datasource": {
            "type": "mssql",
            "uid": "${instance}"
          },
          "format": "time_series",
          "rawQuery": true,
          "rawSql": "SELECT time = DATEADD(MINUTE, DATEDIFF(MINUTE, GETDATE(), GETUTCDATE()), ss.collection_time), total = ss.total_sessions, running = ss.running_sessions, sleeping = ss.sleeping_sessions, waiting_for_memory = ss.sessions_waiting_for_memory FROM collect.session_stats AS ss WHERE ss.collection_time >= DATEADD(MINUTE, DATEDIFF(MINUTE, GETUTCDATE(), GETDATE()), CONVERT(datetime2, $__timeFrom())) AND ss.collection_time < DATEADD(MINUTE, DATEDIFF(MINUTE, GETUTCDATE(), GETDATE()), CONVERT(datetime2, $__timeTo())) ORDER BY ss.collection_time;"
        }
      ]
    },
    {
      "id": 13,
      "type": "timeseries",
      "title": "Top wait types",
      "datasource": {
        "type": "mssql",
        "uid": "${instance}"
      },
      "gridPos": {
        "h": 9,
        "w": 12,
        "x": 0,
        "y": 26
      },
      "fieldConfig": {
        "defaults": {
          "color": {
            "mode": "palette-classic"
          },
          "custom": {
            "drawStyle": "line",
            "lineInterpolation": "smooth",
            "lineWidth": 1,
            "fillOpacity": 12,
            "showPoints": "never",
            "spanNulls": true,
            "stacking": {
              "mode": "none",
              "group": "A"
            }
          },
          "unit": "ms"
        },
        "overrides": []
      },
      "options": {
        "legend": {
          "displayMode": "list",
          "placement": "bottom",
          "showLegend": true,
          "calcs": []
        },
        "tooltip": {
          "mode": "multi",
          "sort": "desc"
        }
      },
      "targets": [
        {
          "refId": "A",
          "datasource": {
            "type": "mssql",
            "uid": "${instance}"
          },
          "format": "time_series",
          "rawQuery": true,
          "rawSql": "\nSELECT\n    time = DATEADD(MINUTE, DATEDIFF(MINUTE, GETDATE(), GETUTCDATE()), ws.collection_time),\n    metric = ws.wait_type,\n    value = CONVERT(float, ws.wait_time_ms_delta)\nFROM collect.wait_stats AS ws\nWHERE ws.collection_time >= DATEADD(MINUTE, DATEDIFF(MINUTE, GETUTCDATE(), GETDATE()), CONVERT(datetime2, $__timeFrom())) AND ws.collection_time < DATEADD(MINUTE, DATEDIFF(MINUTE, GETUTCDATE(), GETDATE()), CONVERT(datetime2, $__timeTo()))\n    AND ws.wait_time_ms_delta > 0\n    AND ws.wait_type IN (\n        SELECT TOP (8)\n            ws2.wait_type\n        FROM collect.wait_stats AS ws2\n        WHERE ws2.collection_time >= DATEADD(MINUTE, DATEDIFF(MINUTE, GETUTCDATE(), GETDATE()), CONVERT(datetime2, $__timeFrom())) AND ws2.collection_time < DATEADD(MINUTE, DATEDIFF(MINUTE, GETUTCDATE(), GETDATE()), CONVERT(datetime2, $__timeTo()))\n        GROUP BY ws2.wait_type\n        ORDER BY SUM(ws2.wait_time_ms_delta) DESC\n    )\nORDER BY ws.collection_time;\n"
        }
      ]
    },
    {
      "id": 14,
      "type": "bargauge",
      "title": "Top waits (last hour)",
      "datasource": {
        "type": "mssql",
        "uid": "${instance}"
      },
      "gridPos": {
        "h": 9,
        "w": 12,
        "x": 12,
        "y": 26
      },
      "fieldConfig": {
        "defaults": {
          "color": {
            "mode": "continuous-GrYlRd"
          },
          "thresholds": {
            "mode": "absolute",
            "steps": [
              {
                "color": "green",
                "value": null
              }
            ]
          },
          "unit": "s"
        },
        "overrides": []
      },
      "options": {
        "displayMode": "gradient",
        "orientation": "horizontal",
        "reduceOptions": {
          "calcs": [
            "lastNotNull"
          ],
          "fields": "/^(?!.*name|.*type).*$/",
          "values": true
        },
        "showUnfilled": true,
        "valueMode": "color",
        "namePlacement": "left"
      },
      "targets": [
        {
          "refId": "A",
          "datasource": {
            "type": "mssql",
            "uid": "${instance}"
          },
          "format": "table",
          "rawQuery": true,
          "rawSql": "SELECT tw.wait_type, wait_seconds = CONVERT(float, tw.wait_time_sec) FROM report.top_waits_last_hour AS tw ORDER BY tw.wait_time_ms DESC;"
        }
      ]
    },
    {
      "id": 15,
      "type": "timeseries",
      "title": "Blocking events & deadlocks",
      "datasource": {
        "type": "mssql",
        "uid": "${instance}"
      },
      "gridPos": {
        "h": 8,
        "w": 12,
        "x": 0,
        "y": 35
      },
      "fieldConfig": {
        "defaults": {
          "color": {
            "mode": "palette-classic"
          },
          "custom": {
            "drawStyle": "bars",
            "lineInterpolation": "smooth",
            "lineWidth": 1,
            "fillOpacity": 80,
            "showPoints": "never",
            "spanNulls": true,
            "stacking": {
              "mode": "none",
              "group": "A"
            }
          },
          "unit": "short"
        },
        "overrides": []
      },
      "options": {
        "legend": {
          "displayMode": "list",
          "placement": "bottom",
          "showLegend": true,
          "calcs": []
        },
        "tooltip": {
          "mode": "multi",
          "sort": "desc"
        }
      },
      "targets": [
        {
          "refId": "A",
          "datasource": {
            "type": "mssql",
            "uid": "${instance}"
          },
          "format": "time_series",
          "rawQuery": true,
          "rawSql": "SELECT time = DATEADD(MINUTE, DATEDIFF(MINUTE, GETDATE(), GETUTCDATE()), bds.collection_time), blocking_events = SUM(bds.blocking_event_count_delta), deadlocks = SUM(bds.deadlock_count_delta) FROM collect.blocking_deadlock_stats AS bds WHERE bds.collection_time >= DATEADD(MINUTE, DATEDIFF(MINUTE, GETUTCDATE(), GETDATE()), CONVERT(datetime2, $__timeFrom())) AND bds.collection_time < DATEADD(MINUTE, DATEDIFF(MINUTE, GETUTCDATE(), GETDATE()), CONVERT(datetime2, $__timeTo())) GROUP BY bds.collection_time ORDER BY bds.collection_time;"
        }
      ]
    },
    {
      "id": 16,
      "type": "table",
      "title": "File IO latency by database",
      "datasource": {
        "type": "mssql",
        "uid": "${instance}"
      },
      "gridPos": {
        "h": 8,
        "w": 12,
        "x": 12,
        "y": 35
      },
      "fieldConfig": {
        "defaults": {
          "custom": {
            "align": "auto",
            "cellOptions": {
              "type": "auto"
            },
            "filterable": true
          },
          "thresholds": {
            "mode": "absolute",
            "steps": [
              {
                "color": "green",
                "value": null
              }
            ]
          }
        },
        "overrides": []
      },
      "options": {
        "showHeader": true,
        "cellHeight": "sm",
        "footer": {
          "show": false,
          "reducer": [
            "sum"
          ],
          "fields": ""
        },
        "sortBy": []
      },
      "targets": [
        {
          "refId": "A",
          "datasource": {
            "type": "mssql",
            "uid": "${instance}"
          },
          "format": "table",
          "rawQuery": true,
          "rawSql": "\nSELECT TOP (20)\n    database_name = fio.database_name,\n    file_type = fio.file_type_desc,\n    reads = SUM(fio.num_of_reads_delta),\n    avg_read_ms = CONVERT(decimal(19,2), SUM(fio.io_stall_read_ms_delta) * 1.0 / NULLIF(SUM(fio.num_of_reads_delta), 0)),\n    writes = SUM(fio.num_of_writes_delta),\n    avg_write_ms = CONVERT(decimal(19,2), SUM(fio.io_stall_write_ms_delta) * 1.0 / NULLIF(SUM(fio.num_of_writes_delta), 0))\nFROM collect.file_io_stats AS fio\nWHERE fio.collection_time >= DATEADD(MINUTE, DATEDIFF(MINUTE, GETUTCDATE(), GETDATE()), CONVERT(datetime2, $__timeFrom())) AND fio.collection_time < DATEADD(MINUTE, DATEDIFF(MINUTE, GETUTCDATE(), GETDATE()), CONVERT(datetime2, $__timeTo()))\nGROUP BY fio.database_name, fio.file_type_desc\nORDER BY SUM(fio.io_stall_ms_delta) DESC;\n"
        }
      ]
    },
    {
      "id": 17,
      "type": "table",
      "title": "CPU spike events (last 48h)",
      "datasource": {
        "type": "mssql",
        "uid": "${instance}"
      },
      "gridPos": {
        "h": 9,
        "w": 12,
        "x": 0,
        "y": 43
      },
      "fieldConfig": {
        "defaults": {
          "custom": {
            "align": "auto",
            "cellOptions": {
              "type": "auto"
            },
            "filterable": true
          },
          "thresholds": {
            "mode": "absolute",
            "steps": [
              {
                "color": "green",
                "value": null
              }
            ]
          }
        },
        "overrides": [
          {
            "matcher": {
              "id": "byName",
              "options": "severity"
            },
            "properties": [
              {
                "id": "mappings",
                "value": [
                  {
                    "type": "value",
                    "options": {
                      "CRITICAL": {
                        "color": "red",
                        "index": 0
                      },
                      "HIGH": {
                        "color": "red",
                        "index": 1
                      },
                      "MEDIUM": {
                        "color": "orange",
                        "index": 2
                      },
                      "LOW": {
                        "color": "green",
                        "index": 3
                      }
                    }
                  }
                ]
              },
              {
                "id": "custom.cellOptions",
                "value": {
                  "type": "color-background"
                }
              }
            ]
          },
          {
            "matcher": {
              "id": "byName",
              "options": "event_time"
            },
            "properties": [
              {
                "id": "links",
                "value": [
                  {
                    "title": "Drill down: queries +/-20min around this spike",
                    "url": "/d/perfmon-queries?from=${__data.fields.window_from_ms}&to=${__data.fields.window_to_ms}&var-instance=${instance}",
                    "targetBlank": false
                  }
                ]
              }
            ]
          },
          {
            "matcher": {
              "id": "byName",
              "options": "window_from_ms"
            },
            "properties": [
              {
                "id": "custom.hidden",
                "value": true
              }
            ]
          },
          {
            "matcher": {
              "id": "byName",
              "options": "window_to_ms"
            },
            "properties": [
              {
                "id": "custom.hidden",
                "value": true
              }
            ]
          }
        ]
      },
      "options": {
        "showHeader": true,
        "cellHeight": "sm",
        "footer": {
          "show": false,
          "reducer": [
            "sum"
          ],
          "fields": ""
        },
        "sortBy": [
          {
            "displayName": "event_time",
            "desc": true
          }
        ]
      },
      "targets": [
        {
          "refId": "A",
          "datasource": {
            "type": "mssql",
            "uid": "${instance}"
          },
          "format": "table",
          "rawQuery": true,
          "rawSql": "\nSELECT TOP (50)\n    cs.event_time,\n    cs.sql_server_cpu,\n    cs.other_process_cpu,\n    cs.total_cpu,\n    cs.severity,\n    window_from_ms = DATEDIFF_BIG(MILLISECOND, '19700101', DATEADD(MINUTE, -20, cs.event_time)),\n    window_to_ms = DATEDIFF_BIG(MILLISECOND, '19700101', DATEADD(MINUTE, 20, cs.event_time))\nFROM report.cpu_spikes AS cs\nWHERE cs.event_time >= DATEADD(HOUR, -48, SYSDATETIME())\n    AND cs.sql_server_cpu >= 60\nORDER BY cs.event_time DESC;\n"
        }
      ]
    },
    {
      "id": 18,
      "type": "table",
      "title": "Scheduler CPU analysis",
      "datasource": {
        "type": "mssql",
        "uid": "${instance}"
      },
      "gridPos": {
        "h": 9,
        "w": 12,
        "x": 12,
        "y": 43
      },
      "fieldConfig": {
        "defaults": {
          "custom": {
            "align": "auto",
            "cellOptions": {
              "type": "auto"
            },
            "filterable": true
          },
          "thresholds": {
            "mode": "absolute",
            "steps": [
              {
                "color": "green",
                "value": null
              }
            ]
          }
        },
        "overrides": [
          {
            "matcher": {
              "id": "byName",
              "options": "cpu_pressure_level"
            },
            "properties": [
              {
                "id": "mappings",
                "value": [
                  {
                    "type": "value",
                    "options": {
                      "CRITICAL - Worker thread exhaustion detected": {
                        "color": "red",
                        "index": 0
                      },
                      "CRITICAL - High runnable task queue": {
                        "color": "red",
                        "index": 1
                      },
                      "HIGH - Frequent runnable task warnings": {
                        "color": "red",
                        "index": 2
                      },
                      "HIGH - Sustained runnable task queue": {
                        "color": "orange",
                        "index": 3
                      },
                      "MEDIUM - Blocked tasks": {
                        "color": "orange",
                        "index": 4
                      },
                      "NORMAL": {
                        "color": "green",
                        "index": 5
                      }
                    }
                  }
                ]
              },
              {
                "id": "custom.cellOptions",
                "value": {
                  "type": "color-background"
                }
              }
            ]
          }
        ]
      },
      "options": {
        "showHeader": true,
        "cellHeight": "sm",
        "footer": {
          "show": false,
          "reducer": [
            "sum"
          ],
          "fields": ""
        },
        "sortBy": []
      },
      "targets": [
        {
          "refId": "A",
          "datasource": {
            "type": "mssql",
            "uid": "${instance}"
          },
          "format": "table",
          "rawQuery": true,
          "rawSql": "\nSELECT\n    sca.collection_time,\n    sca.scheduler_count,\n    sca.cpu_count,\n    sca.total_current_workers_count,\n    sca.max_workers_count,\n    worker_utilization_percent = sca.worker_utilization_percent,\n    sca.total_runnable_tasks_count,\n    sca.avg_runnable_tasks_count,\n    sca.total_blocked_task_count,\n    avg_runnable_tasks_1h = sca.avg_runnable_tasks,\n    max_runnable_tasks_1h = sca.max_runnable_tasks,\n    sca.cpu_pressure_level,\n    sca.recommendation\nFROM report.scheduler_cpu_analysis AS sca;\n"
        }
      ]
    },
    {
      "id": 19,
      "type": "row",
      "title": "Daily Summary",
      "collapsed": false,
      "gridPos": {
        "h": 1,
        "w": 24,
        "x": 0,
        "y": 52
      },
      "panels": []
    },
    {
      "id": 20,
      "type": "table",
      "title": "Daily summary",
      "datasource": {
        "type": "mssql",
        "uid": "${instance}"
      },
      "gridPos": {
        "h": 9,
        "w": 24,
        "x": 0,
        "y": 53
      },
      "fieldConfig": {
        "defaults": {
          "custom": {
            "align": "auto",
            "cellOptions": {
              "type": "auto"
            },
            "filterable": true
          },
          "thresholds": {
            "mode": "absolute",
            "steps": [
              {
                "color": "green",
                "value": null
              }
            ]
          }
        },
        "overrides": []
      },
      "options": {
        "showHeader": true,
        "cellHeight": "sm",
        "footer": {
          "show": false,
          "reducer": [
            "sum"
          ],
          "fields": ""
        },
        "sortBy": []
      },
      "targets": [
        {
          "refId": "A",
          "datasource": {
            "type": "mssql",
            "uid": "${instance}"
          },
          "format": "table",
          "rawQuery": true,
          "rawSql": "SELECT ds.sort_order, ds.metric_name, metric_value = CONVERT(nvarchar(500), ds.metric_value) FROM report.daily_summary_v2 AS ds ORDER BY ds.sort_order;"
        }
      ]
    },
    {
      "id": 21,
      "type": "table",
      "title": "Server configuration changes",
      "datasource": {
        "type": "mssql",
        "uid": "${instance}"
      },
      "gridPos": {
        "h": 9,
        "w": 24,
        "x": 0,
        "y": 103
      },
      "fieldConfig": {
        "defaults": {
          "custom": {
            "align": "auto",
            "cellOptions": {
              "type": "auto"
            },
            "filterable": true
          },
          "thresholds": {
            "mode": "absolute",
            "steps": [
              {
                "color": "green",
                "value": null
              }
            ]
          }
        },
        "overrides": []
      },
      "options": {
        "showHeader": true,
        "cellHeight": "sm",
        "footer": {
          "show": false,
          "reducer": [
            "sum"
          ],
          "fields": ""
        },
        "sortBy": [
          {
            "displayName": "change_time",
            "desc": true
          }
        ]
      },
      "targets": [
        {
          "refId": "A",
          "datasource": {
            "type": "mssql",
            "uid": "${instance}"
          },
          "format": "table",
          "rawQuery": true,
          "rawSql": "\nSELECT TOP (100)\n    scc.change_time,\n    scc.configuration_name,\n    scc.old_value_configured,\n    scc.new_value_configured,\n    scc.old_value_in_use,\n    scc.new_value_in_use,\n    scc.requires_restart,\n    scc.is_dynamic,\n    scc.is_advanced,\n    scc.description,\n    scc.change_description\nFROM report.server_configuration_changes AS scc\nWHERE scc.change_time >= DATEADD(MINUTE, DATEDIFF(MINUTE, GETUTCDATE(), GETDATE()), CONVERT(datetime2, $__timeFrom())) AND scc.change_time < DATEADD(MINUTE, DATEDIFF(MINUTE, GETUTCDATE(), GETDATE()), CONVERT(datetime2, $__timeTo()))\nORDER BY scc.change_time DESC;\n"
        }
      ]
    },
    {
      "id": 22,
      "type": "table",
      "title": "Database configuration changes",
      "datasource": {
        "type": "mssql",
        "uid": "${instance}"
      },
      "gridPos": {
        "h": 9,
        "w": 12,
        "x": 0,
        "y": 112
      },
      "fieldConfig": {
        "defaults": {
          "custom": {
            "align": "auto",
            "cellOptions": {
              "type": "auto"
            },
            "filterable": true
          },
          "thresholds": {
            "mode": "absolute",
            "steps": [
              {
                "color": "green",
                "value": null
              }
            ]
          }
        },
        "overrides": []
      },
      "options": {
        "showHeader": true,
        "cellHeight": "sm",
        "footer": {
          "show": false,
          "reducer": [
            "sum"
          ],
          "fields": ""
        },
        "sortBy": [
          {
            "displayName": "change_time",
            "desc": true
          }
        ]
      },
      "targets": [
        {
          "refId": "A",
          "datasource": {
            "type": "mssql",
            "uid": "${instance}"
          },
          "format": "table",
          "rawQuery": true,
          "rawSql": "\nSELECT TOP (100)\n    dcc.change_time,\n    dcc.database_name,\n    dcc.setting_type,\n    dcc.setting_name,\n    dcc.old_value,\n    dcc.new_value,\n    dcc.change_description\nFROM report.database_configuration_changes AS dcc\nWHERE dcc.change_time >= DATEADD(MINUTE, DATEDIFF(MINUTE, GETUTCDATE(), GETDATE()), CONVERT(datetime2, $__timeFrom())) AND dcc.change_time < DATEADD(MINUTE, DATEDIFF(MINUTE, GETUTCDATE(), GETDATE()), CONVERT(datetime2, $__timeTo()))\nORDER BY dcc.change_time DESC;\n"
        }
      ]
    },
    {
      "id": 23,
      "type": "row",
      "title": "Recommendations",
      "collapsed": false,
      "gridPos": {
        "h": 1,
        "w": 24,
        "x": 0,
        "y": 62
      },
      "panels": []
    },
    {
      "id": 24,
      "type": "table",
      "title": "Critical issues",
      "datasource": {
        "type": "mssql",
        "uid": "${instance}"
      },
      "gridPos": {
        "h": 9,
        "w": 24,
        "x": 0,
        "y": 63
      },
      "fieldConfig": {
        "defaults": {
          "custom": {
            "align": "auto",
            "cellOptions": {
              "type": "auto"
            },
            "filterable": true
          },
          "thresholds": {
            "mode": "absolute",
            "steps": [
              {
                "color": "green",
                "value": null
              }
            ]
          }
        },
        "overrides": [
          {
            "matcher": {
              "id": "byName",
              "options": "severity"
            },
            "properties": [
              {
                "id": "mappings",
                "value": [
                  {
                    "type": "value",
                    "options": {
                      "CRITICAL": {
                        "color": "red",
                        "index": 0
                      },
                      "WARNING": {
                        "color": "orange",
                        "index": 1
                      },
                      "INFO": {
                        "color": "blue",
                        "index": 2
                      }
                    }
                  }
                ]
              },
              {
                "id": "custom.cellOptions",
                "value": {
                  "type": "color-background"
                }
              }
            ]
          },
          {
            "matcher": {
              "id": "byName",
              "options": "problem_area"
            },
            "properties": [
              {
                "id": "links",
                "value": [
                  {
                    "title": "Investigate in dashboard",
                    "url": "${__data.fields.problem_area_url}?${__data.fields.problem_area_qs}from=${__data.fields.window_from_ms}&to=${__data.fields.window_to_ms}&var-instance=${instance}",
                    "targetBlank": false
                  }
                ]
              }
            ]
          },
          {
            "matcher": {
              "id": "byName",
              "options": "problem_area_url"
            },
            "properties": [
              {
                "id": "custom.hidden",
                "value": true
              }
            ]
          },
          {
            "matcher": {
              "id": "byName",
              "options": "problem_area_qs"
            },
            "properties": [
              {
                "id": "custom.hidden",
                "value": true
              }
            ]
          },
          {
            "matcher": {
              "id": "byName",
              "options": "window_from_ms"
            },
            "properties": [
              {
                "id": "custom.hidden",
                "value": true
              }
            ]
          },
          {
            "matcher": {
              "id": "byName",
              "options": "window_to_ms"
            },
            "properties": [
              {
                "id": "custom.hidden",
                "value": true
              }
            ]
          }
        ]
      },
      "options": {
        "showHeader": true,
        "cellHeight": "sm",
        "footer": {
          "show": false,
          "reducer": [
            "sum"
          ],
          "fields": ""
        },
        "sortBy": [
          {
            "displayName": "log_date",
            "desc": true
          }
        ]
      },
      "targets": [
        {
          "refId": "A",
          "datasource": {
            "type": "mssql",
            "uid": "${instance}"
          },
          "format": "table",
          "rawQuery": true,
          "rawSql": "\nSELECT TOP (100)\n    ci.issue_id,\n    ci.log_date,\n    ci.severity,\n    ci.problem_area,\n    ci.source_collector,\n    ci.affected_database,\n    ci.message,\n    ci.investigate_query,\n    ci.threshold_value,\n    ci.threshold_limit,\n    problem_area_url =\n        CASE ci.problem_area\n            WHEN N'Blocking' THEN N'/d/perfmon-blocking'\n            WHEN N'Deadlocking' THEN N'/d/perfmon-blocking'\n            WHEN N'Blocking and Deadlocking' THEN N'/d/perfmon-blocking'\n            WHEN N'Query Store Configuration' THEN N'/d/perfmon-queries'\n            WHEN N'Memory Clerk Growth' THEN N'/d/perfmon-memory'\n            WHEN N'SQL Server Stability' THEN N'/d/perfmon-system-events'\n            WHEN N'Database Configuration' THEN N'/d/perfmon-instance'\n            WHEN N'Server Configuration' THEN N'/d/perfmon-instance'\n            ELSE N'/d/perfmon-instance'\n        END,\n    problem_area_qs =\n        CASE ci.problem_area\n            WHEN N'Database Configuration' THEN N'viewPanel=22&'\n            WHEN N'Server Configuration' THEN N'viewPanel=21&'\n            ELSE N''\n        END,\n    window_from_ms = DATEDIFF_BIG(MILLISECOND, '19700101', DATEADD(MINUTE, -20, ci.log_date)),\n    window_to_ms = DATEDIFF_BIG(MILLISECOND, '19700101', DATEADD(MINUTE, 20, ci.log_date))\nFROM config.critical_issues AS ci\nWHERE ci.log_date >= DATEADD(HOUR, -24, SYSDATETIME())\nORDER BY ci.log_date DESC;\n"
        }
      ]
    },
    {
      "id": 25,
      "type": "row",
      "title": "Default Trace",
      "collapsed": false,
      "gridPos": {
        "h": 1,
        "w": 24,
        "x": 0,
        "y": 72
      },
      "panels": []
    },
    {
      "id": 26,
      "type": "table",
      "title": "Default trace events",
      "datasource": {
        "type": "mssql",
        "uid": "${instance}"
      },
      "gridPos": {
        "h": 9,
        "w": 24,
        "x": 0,
        "y": 73
      },
      "fieldConfig": {
        "defaults": {
          "custom": {
            "align": "auto",
            "cellOptions": {
              "type": "auto"
            },
            "filterable": true
          },
          "thresholds": {
            "mode": "absolute",
            "steps": [
              {
                "color": "green",
                "value": null
              }
            ]
          }
        },
        "overrides": []
      },
      "options": {
        "showHeader": true,
        "cellHeight": "sm",
        "footer": {
          "show": false,
          "reducer": [
            "sum"
          ],
          "fields": ""
        },
        "sortBy": [
          {
            "displayName": "event_time",
            "desc": true
          }
        ]
      },
      "targets": [
        {
          "refId": "A",
          "datasource": {
            "type": "mssql",
            "uid": "${instance}"
          },
          "format": "table",
          "rawQuery": true,
          "rawSql": "\nSELECT TOP (100)\n    dte.event_id,\n    dte.collection_time,\n    dte.event_time,\n    dte.event_class,\n    dte.event_name,\n    dte.spid,\n    dte.database_name,\n    dte.database_id,\n    dte.login_name,\n    dte.session_login_name,\n    dte.host_name,\n    dte.application_name,\n    dte.server_name,\n    dte.object_name,\n    dte.filename,\n    dte.integer_data,\n    dte.integer_data_2,\n    dte.text_data,\n    dte.error_number,\n    dte.severity,\n    dte.state,\n    dte.event_sequence,\n    dte.is_system,\n    dte.request_id,\n    dte.duration_us,\n    dte.end_time\nFROM collect.default_trace_events AS dte\nWHERE dte.collection_time >= DATEADD(MINUTE, -10, CONVERT(datetime2, $__timeFrom()))\n    AND dte.collection_time <= DATEADD(MINUTE, 10, CONVERT(datetime2, $__timeTo()))\n    AND dte.event_time >= DATEADD(MINUTE, DATEDIFF(MINUTE, GETUTCDATE(), GETDATE()), CONVERT(datetime2, $__timeFrom())) AND dte.event_time < DATEADD(MINUTE, DATEDIFF(MINUTE, GETUTCDATE(), GETDATE()), CONVERT(datetime2, $__timeTo()))\nORDER BY dte.event_time DESC;\n"
        }
      ]
    },
    {
      "id": 27,
      "type": "row",
      "title": "Current Configuration",
      "collapsed": false,
      "gridPos": {
        "h": 1,
        "w": 24,
        "x": 0,
        "y": 82
      },
      "panels": []
    },
    {
      "id": 28,
      "type": "table",
      "title": "Server configuration (latest values)",
      "datasource": {
        "type": "mssql",
        "uid": "${instance}"
      },
      "gridPos": {
        "h": 10,
        "w": 24,
        "x": 0,
        "y": 83
      },
      "fieldConfig": {
        "defaults": {
          "custom": {
            "align": "auto",
            "cellOptions": {
              "type": "auto"
            },
            "filterable": true
          },
          "thresholds": {
            "mode": "absolute",
            "steps": [
              {
                "color": "green",
                "value": null
              }
            ]
          }
        },
        "overrides": []
      },
      "options": {
        "showHeader": true,
        "cellHeight": "sm",
        "footer": {
          "show": false,
          "reducer": [
            "sum"
          ],
          "fields": ""
        },
        "sortBy": []
      },
      "targets": [
        {
          "refId": "A",
          "datasource": {
            "type": "mssql",
            "uid": "${instance}"
          },
          "format": "table",
          "rawQuery": true,
          "rawSql": "\nSELECT\n    x.configuration_name,\n    x.value_configured,\n    x.value_in_use,\n    x.value_minimum,\n    x.value_maximum,\n    x.is_dynamic,\n    x.is_advanced,\n    x.description,\n    x.collection_time\nFROM (\n    SELECT\n        sch.*,\n        rn = ROW_NUMBER() OVER (PARTITION BY sch.configuration_id ORDER BY sch.collection_time DESC)\n    FROM config.server_configuration_history AS sch\n) AS x\nWHERE x.rn = 1\nORDER BY x.configuration_name;\n"
        }
      ]
    },
    {
      "id": 29,
      "type": "table",
      "title": "Database configuration (latest values)",
      "datasource": {
        "type": "mssql",
        "uid": "${instance}"
      },
      "gridPos": {
        "h": 9,
        "w": 12,
        "x": 0,
        "y": 93
      },
      "fieldConfig": {
        "defaults": {
          "custom": {
            "align": "auto",
            "cellOptions": {
              "type": "auto"
            },
            "filterable": true
          },
          "thresholds": {
            "mode": "absolute",
            "steps": [
              {
                "color": "green",
                "value": null
              }
            ]
          }
        },
        "overrides": []
      },
      "options": {
        "showHeader": true,
        "cellHeight": "sm",
        "footer": {
          "show": false,
          "reducer": [
            "sum"
          ],
          "fields": ""
        },
        "sortBy": []
      },
      "targets": [
        {
          "refId": "A",
          "datasource": {
            "type": "mssql",
            "uid": "${instance}"
          },
          "format": "table",
          "rawQuery": true,
          "rawSql": "\nSELECT\n    x.database_name,\n    x.setting_type,\n    x.setting_name,\n    x.setting_value,\n    x.collection_time\nFROM (\n    SELECT\n        dch.*,\n        rn = ROW_NUMBER() OVER (PARTITION BY dch.database_name, dch.setting_type, dch.setting_name ORDER BY dch.collection_time DESC)\n    FROM config.database_configuration_history AS dch\n) AS x\nWHERE x.rn = 1\nORDER BY x.database_name, x.setting_type, x.setting_name;\n"
        }
      ]
    },
    {
      "id": 30,
      "type": "table",
      "title": "Trace flags (latest values)",
      "datasource": {
        "type": "mssql",
        "uid": "${instance}"
      },
      "gridPos": {
        "h": 9,
        "w": 12,
        "x": 12,
        "y": 93
      },
      "fieldConfig": {
        "defaults": {
          "custom": {
            "align": "auto",
            "cellOptions": {
              "type": "auto"
            },
            "filterable": true
          },
          "thresholds": {
            "mode": "absolute",
            "steps": [
              {
                "color": "green",
                "value": null
              }
            ]
          }
        },
        "overrides": []
      },
      "options": {
        "showHeader": true,
        "cellHeight": "sm",
        "footer": {
          "show": false,
          "reducer": [
            "sum"
          ],
          "fields": ""
        },
        "sortBy": []
      },
      "targets": [
        {
          "refId": "A",
          "datasource": {
            "type": "mssql",
            "uid": "${instance}"
          },
          "format": "table",
          "rawQuery": true,
          "rawSql": "\nSELECT\n    x.trace_flag,\n    x.status,\n    x.is_global,\n    x.is_session,\n    x.collection_time\nFROM (\n    SELECT\n        tfh.*,\n        rn = ROW_NUMBER() OVER (PARTITION BY tfh.trace_flag ORDER BY tfh.collection_time DESC)\n    FROM config.trace_flags_history AS tfh\n) AS x\nWHERE x.rn = 1\nORDER BY x.trace_flag;\n"
        }
      ]
    },
    {
      "id": 31,
      "type": "row",
      "title": "Configuration Changes",
      "collapsed": false,
      "gridPos": {
        "h": 1,
        "w": 24,
        "x": 0,
        "y": 102
      },
      "panels": []
    },
    {
      "id": 32,
      "type": "table",
      "title": "Trace flag changes",
      "datasource": {
        "type": "mssql",
        "uid": "${instance}"
      },
      "gridPos": {
        "h": 9,
        "w": 12,
        "x": 12,
        "y": 112
      },
      "fieldConfig": {
        "defaults": {
          "custom": {
            "align": "auto",
            "cellOptions": {
              "type": "auto"
            },
            "filterable": true
          },
          "thresholds": {
            "mode": "absolute",
            "steps": [
              {
                "color": "green",
                "value": null
              }
            ]
          }
        },
        "overrides": []
      },
      "options": {
        "showHeader": true,
        "cellHeight": "sm",
        "footer": {
          "show": false,
          "reducer": [
            "sum"
          ],
          "fields": ""
        },
        "sortBy": [
          {
            "displayName": "change_time",
            "desc": true
          }
        ]
      },
      "targets": [
        {
          "refId": "A",
          "datasource": {
            "type": "mssql",
            "uid": "${instance}"
          },
          "format": "table",
          "rawQuery": true,
          "rawSql": "\nSELECT TOP (100)\n    tfc.change_time,\n    tfc.trace_flag,\n    tfc.previous_status,\n    tfc.new_status,\n    tfc.is_global,\n    tfc.is_session,\n    tfc.scope,\n    tfc.change_description\nFROM report.trace_flag_changes AS tfc\nWHERE tfc.change_time >= DATEADD(MINUTE, DATEDIFF(MINUTE, GETUTCDATE(), GETDATE()), CONVERT(datetime2, $__timeFrom())) AND tfc.change_time < DATEADD(MINUTE, DATEDIFF(MINUTE, GETUTCDATE(), GETDATE()), CONVERT(datetime2, $__timeTo()))\nORDER BY tfc.change_time DESC;\n"
        }
      ]
    },
    {
      "id": 33,
      "type": "row",
      "title": "Collection Health",
      "collapsed": false,
      "gridPos": {
        "h": 1,
        "w": 24,
        "x": 0,
        "y": 121
      },
      "panels": []
    },
    {
      "id": 34,
      "type": "table",
      "title": "Collection health",
      "datasource": {
        "type": "mssql",
        "uid": "${instance}"
      },
      "gridPos": {
        "h": 10,
        "w": 24,
        "x": 0,
        "y": 122
      },
      "fieldConfig": {
        "defaults": {
          "custom": {
            "align": "auto",
            "cellOptions": {
              "type": "auto"
            },
            "filterable": true
          },
          "thresholds": {
            "mode": "absolute",
            "steps": [
              {
                "color": "green",
                "value": null
              }
            ]
          }
        },
        "overrides": [
          {
            "matcher": {
              "id": "byName",
              "options": "health_status"
            },
            "properties": [
              {
                "id": "mappings",
                "value": [
                  {
                    "type": "value",
                    "options": {
                      "FAILING": {
                        "color": "red",
                        "index": 0
                      },
                      "STALE": {
                        "color": "orange",
                        "index": 1
                      },
                      "NEVER_RUN": {
                        "color": "yellow",
                        "index": 2
                      },
                      "OK": {
                        "color": "green",
                        "index": 3
                      }
                    }
                  }
                ]
              },
              {
                "id": "custom.cellOptions",
                "value": {
                  "type": "color-background"
                }
              }
            ]
          }
        ]
      },
      "options": {
        "showHeader": true,
        "cellHeight": "sm",
        "footer": {
          "show": false,
          "reducer": [
            "sum"
          ],
          "fields": ""
        },
        "sortBy": []
      },
      "targets": [
        {
          "refId": "A",
          "datasource": {
            "type": "mssql",
            "uid": "${instance}"
          },
          "format": "table",
          "rawQuery": true,
          "rawSql": "\nSELECT\n    ch.collector_name,\n    ch.health_status,\n    ch.last_success_time,\n    ch.hours_since_success,\n    ch.failure_rate_percent,\n    ch.avg_duration_ms\nFROM report.collection_health AS ch\nORDER BY\n    CASE ch.health_status\n        WHEN N'FAILING' THEN 0\n        WHEN N'STALE' THEN 1\n        WHEN N'NEVER_RUN' THEN 2\n        ELSE 3\n    END,\n    ch.collector_name;\n"
        }
      ]
    },
    {
      "id": 35,
      "type": "timeseries",
      "title": "Duration Trends",
      "datasource": {
        "type": "mssql",
        "uid": "${instance}"
      },
      "gridPos": {
        "h": 9,
        "w": 24,
        "x": 0,
        "y": 132
      },
      "fieldConfig": {
        "defaults": {
          "color": {
            "mode": "palette-classic"
          },
          "custom": {
            "drawStyle": "line",
            "lineInterpolation": "smooth",
            "lineWidth": 1,
            "fillOpacity": 12,
            "showPoints": "never",
            "spanNulls": true,
            "stacking": {
              "mode": "none",
              "group": "A"
            }
          },
          "unit": "ms"
        },
        "overrides": []
      },
      "options": {
        "legend": {
          "displayMode": "list",
          "placement": "bottom",
          "showLegend": true,
          "calcs": []
        },
        "tooltip": {
          "mode": "multi",
          "sort": "desc"
        }
      },
      "targets": [
        {
          "refId": "A",
          "datasource": {
            "type": "mssql",
            "uid": "${instance}"
          },
          "format": "time_series",
          "rawQuery": true,
          "rawSql": "SELECT time = DATEADD(MINUTE, DATEDIFF(MINUTE, GETDATE(), GETUTCDATE()), cl.collection_time), metric = cl.collector_name, value = CONVERT(float, cl.duration_ms) FROM config.collection_log AS cl WHERE cl.collection_status = N'SUCCESS' AND cl.duration_ms IS NOT NULL AND cl.collection_time >= DATEADD(MINUTE, DATEDIFF(MINUTE, GETUTCDATE(), GETDATE()), CONVERT(datetime2, $__timeFrom())) AND cl.collection_time < DATEADD(MINUTE, DATEDIFF(MINUTE, GETUTCDATE(), GETDATE()), CONVERT(datetime2, $__timeTo())) ORDER BY cl.collection_time;"
        }
      ]
    },
    {
      "id": 36,
      "type": "row",
      "title": "Running Jobs",
      "collapsed": false,
      "gridPos": {
        "h": 1,
        "w": 24,
        "x": 0,
        "y": 141
      },
      "panels": []
    },
    {
      "id": 37,
      "type": "table",
      "title": "Running SQL Agent jobs",
      "datasource": {
        "type": "mssql",
        "uid": "${instance}"
      },
      "gridPos": {
        "h": 9,
        "w": 24,
        "x": 0,
        "y": 142
      },
      "fieldConfig": {
        "defaults": {
          "custom": {
            "align": "auto",
            "cellOptions": {
              "type": "auto"
            },
            "filterable": true
          },
          "thresholds": {
            "mode": "absolute",
            "steps": [
              {
                "color": "green",
                "value": null
              }
            ]
          }
        },
        "overrides": [
          {
            "matcher": {
              "id": "byName",
              "options": "duration_status"
            },
            "properties": [
              {
                "id": "mappings",
                "value": [
                  {
                    "type": "value",
                    "options": {
                      "LONG RUNNING": {
                        "color": "red",
                        "index": 0
                      },
                      "ABOVE AVERAGE": {
                        "color": "orange",
                        "index": 1
                      },
                      "NO HISTORY": {
                        "color": "yellow",
                        "index": 2
                      },
                      "NORMAL": {
                        "color": "green",
                        "index": 3
                      }
                    }
                  }
                ]
              },
              {
                "id": "custom.cellOptions",
                "value": {
                  "type": "color-background"
                }
              }
            ]
          }
        ]
      },
      "options": {
        "showHeader": true,
        "cellHeight": "sm",
        "footer": {
          "show": false,
          "reducer": [
            "sum"
          ],
          "fields": ""
        },
        "sortBy": []
      },
      "targets": [
        {
          "refId": "A",
          "datasource": {
            "type": "mssql",
            "uid": "${instance}"
          },
          "format": "table",
          "rawQuery": true,
          "rawSql": "\nSELECT\n    rj.job_name,\n    rj.job_id,\n    rj.job_enabled,\n    rj.start_time,\n    current_duration = rj.current_duration_formatted,\n    rj.current_duration_seconds,\n    avg_duration = rj.avg_duration_formatted,\n    rj.avg_duration_seconds,\n    p95_duration = rj.p95_duration_formatted,\n    rj.successful_run_count,\n    rj.is_running_long,\n    pct_of_avg = rj.percent_of_average,\n    rj.duration_status\nFROM report.running_jobs AS rj\nORDER BY\n    CASE rj.duration_status\n        WHEN N'LONG RUNNING' THEN 0\n        WHEN N'ABOVE AVERAGE' THEN 1\n        ELSE 3\n    END,\n    rj.current_duration_seconds DESC;\n"
        }
      ]
    }
  ]
}
